{
  "languageCode": "gu",
  "languageName": "Gujarati",
  "langageNameShort": "GUJ",
  "dateLocale": "gu",
  "emoji": "🇮🇳",
  "or": "અથવા",
  "from": "થી",
  "to": "સુધી",
  "for": "માટે",
  "at": "પર",
  "status": "સ્થિતિ",
  "statusPage": "સ્થિતિ પૃષ્ઠ",
  "isDown": "સમસ્યાઓનો અનુભવ થઈ રહ્યો છે",
  "isDisrupted": "વિક્ષેપોનો અનુભવ થઈ રહ્યો છે",
  "isNotice": "જાળવણી ચાલુ છે",
  "isOk": "બધી સિસ્ટમો કાર્યરત છે",
  "operational": "કાર્યરત",
  "underMaintenance": "જાળવણી હેઠળ",
  "degradedPerformance": "ઘટેલું પ્રદર્શન",
  "partialOutage": "આંશિક આઉટેજ",
  "minorOutage": "નાની આઉટેજ",
  "majorOutage": "મોટી આઉટેજ",
  "systemMetrics": "સિસ્ટમ મેટ્રિક્સ",
  "incidents": "અગાઉની ઘટનાઓ",
  "incidentHistory": "ઘટના ઇતિહાસ",
  "incidentDetails": "ઘટના વિગતો",
  "maintenances": "જાળવણીઓ",
  "maintenanceHistory": "જાળવણી ઇતિહાસ",
  "maintenanceDetails": "જાળવણી વિગતો",
  "started": "શરૂ થયું",
  "scheduledFor": "માટે નિર્ધારિત",
  "updated": "અપડેટ કર્યું",
  "resolvedAfter": "આટલા સમય પછી ઉકેલાયું",
  "inUnderAMinute": "એક મિનિટથી ઓછા સમયમાં",
  "ofDowntime": "ડાઉનટાઇમનો",
  "notResolved": "હજુ ઉકેલાયું નથી.",
  "affected": "પ્રભાવિત",
  "affects": "અસર કરે છે",
  "noDowntime": "કોઈ ડાઉનટાઇમ નોંધાયો નથી",
  "didntStart": "સેવા હજુ શરૂ થઈ નથી",
  "dayDidntStart": "દિવસ હજુ શરૂ થયો નથી",
  "noIncidents": "કોઈ ઘટના નોંધાઈ નથી",
  "noIncidentsMonth": "આ મહિને કોઈ ઘટના નોંધાઈ નથી.",
  "noIncidentsWeek": "છેલ્લા 7 દિવસમાં કોઈ ઘટના નોંધાઈ નથી.",
  "prev": "પાછળ",
  "next": "આગળ",
  "goBack": "પાછા જાઓ",
  "poweredBy": "દ્વારા સંચાલિત",
  "showIncidentHistory": "ઘટના ઇતિહાસ બતાવો",
  "showCurrent": "વર્તમાન સ્થિતિ બતાવો",
  "getUpdates": "અપડેટ્સ મેળવો",
  "getUpdatesBy": "આના દ્વારા અપડેટ્સ મેળવો",
  "toAllComponents": "બધી સ્થિતિ અપડેટ્સ મેળવો",
  "toCertainComponents": "ફક્ત ચોક્કસ ઘટકો",
  "subscribe": "સબ્સ્ક્રાઇબ કરો",
  "working": "કાર્ય ચાલુ છે…",
  "subscribed": "તમે હવે સબ્સ્ક્રાઇબ થયા છો",
  "getStatusUpdates": "સ્થિતિ અપડેટ્સ મેળવો",
  "email": "ઇમેઇલ",
  "getUpdatesEmailShort": "ઇમેઇલ દ્વારા અપડેટ્સ મેળવો",
  "getUpdatesEmailLong": "તમારા ઇનબોક્સમાં અપડેટ્સ મેળવો",
  "sms": "SMS",
  "getUpdatesSmsShort": "SMS દ્વારા અપડેટ્સ મેળવો",
  "getUpdatesSmsLong": "તમારા ફોન પર અપડેટ્સ મેળવો",
  "rss": "RSS",
  "webhook": "Webhook",
  "atom": "Atom",
  "feed": "ફીડ",
  "getUpdatesRss": "RSS દ્વારા અપડેટ્સ મેળવો",
  "twitter": "Twitter",
  "getUpdatesTwitterShort": "Twitter પર અપડેટ્સ ફોલો કરો",
  "getUpdatesTwitterLong": "અપડેટ્સ માટે અમને ફોલો કરો",
  "slack": "Slack",
  "getUpdatesSlackShort": "Slack પર અપડેટ્સ મેળવો",
  "getUpdatesSlackLong": "તમારી ચેનલમાં અપડેટ્સ મેળવો",
  "discord": "Discord",
  "getUpdatesDiscordShort": "Discord પર અપડેટ્સ મેળવો",
  "getUpdatesDiscordLong": "તમારી ચેનલમાં અપડેટ્સ મેળવો",
  "microsoftTeams": "Microsoft Teams",
  "getUpdatesMicrosoftTeamsShort": "તમારી ચેનલમાં અપડેટ્સ મેળવો",
  "getUpdatesMicrosoftTeamsLong": "તમારી ચેનલમાં અપડેટ્સ મેળવો",
  "learnMicrosoftTeamsWebhook": "તમારી Microsoft Teams ચેનલમાં webhook કેવી રીતે ઉમેરવું તે શીખો",
  "microsoftTeamsSend": "જ્યારે અમે અમારી સ્થિતિ અપડેટ કરીએ છીએ, ત્યારે અમે તમારી Microsoft Teams ચેનલમાં અપડેટ્સ મોકલીશું.",
  "language": "ભાષા",
  "darkMode": "ડાર્ક મોડ",
  "lightMode": "લાઇટ મોડ",
  "reportAnIssue": "સમસ્યાની જાણ કરો",
  "copied": "કૉપિ કર્યું",
  "toClipboard": "ક્લિપબોર્ડ પર!",
  "emailAddress": "ઇમેઇલ સરનામું",
  "emailExample": "you@yourdomain.com",
  "checkYourEmail": "તમારું ઇમેઇલ તપાસો",
  "weJustSentYouAnEmail": "અમે હમણાં જ તમારા સબ્સ્ક્રિપ્શનની પુષ્ટિ કરવા માટે તમને એક ઇમેઇલ મોકલ્યો છે.",
  "emailConfirmed": "તમારું ઇમેઇલ પુષ્ટિ થયું છે",
  "confirmYourSubscription": "તમારા સબ્સ્ક્રિપ્શનની પુષ્ટિ કરો",
  "allDone": "બધું થઈ ગયું!",
  "wellSendYouAMessage": "જ્યારે અમે અમારી સ્થિતિ અપડેટ કરીએ છીએ, ત્યારે અમે તમને એક ટેક્સ્ટ સંદેશ મોકલીશું.",
  "wellSendYouAnEmail": "જ્યારે અમે અમારી સ્થિતિ અપડેટ કરીએ છીએ, ત્યારે અમે તમને એક ઇમેઇલ મોકલીશું.",
  "webhookUrl": "Webhook URL",
  "webhookDescription": "અમે આ ફોર્મેટનો ઉપયોગ કરીને તમારા URL પર વિનંતીઓ મોકલીશું",
  "webhookFormat": "આ ફોર્મેટ",
  "webhookSendEmail": "જ્યારે તમારા URL સાથે કોઈ સમસ્યા હશે ત્યારે અમે તમને ઇમેઇલ કરીશું",
  "webhookSend": "જ્યારે અમે અમારી સ્થિતિ અપડેટ કરીએ છીએ, ત્યારે અમે તમારા Webhook URL પર અપડેટ્સ મોકલીશું.",
  "webhookFormatLink": "વિનંતી ફોર્મેટ તપાસો",
  "enterEmailError": "કૃપા કરીને તમારું ઇમેઇલ સરનામું દાખલ કરો.",
  "enterPhoneError": "કૃપા કરીને તમારો ફોન નંબર દાખલ કરો.",
  "invalidEmailError": "કૃપા કરીને માન્ય ઇમેઇલ સરનામું દાખલ કરો.",
  "resolved": "ઉકેલાયું",
  "investigating": "તપાસ ચાલુ છે",
  "identified": "ઓળખાયું",
  "monitoring": "નિરીક્ષણ",
  "notstartedyet": "આયોજિત",
  "inprogress": "ચાલુ છે",
  "completed": "પૂર્ણ થયું",
  "update": "અપડેટ",
  "verifying": "ચકાસણી ચાલુ છે",
  "scheduled": "નિર્ધારિત",
  "today": "આજે",
  "daysAgo": "દિવસ પહેલાં",
  "uptime": "અપટાઇમ",
  "numDaysAgo": "{{num}} દિવસ પહેલાં",
  "nextMonths": "આગામી મહિના",
  "nextPage": "આગળનું પૃષ્ઠ",
  "previousPage": "પાછલું પૃષ્ઠ",
  "previousMonths": "પાછલા મહિના",
  "90DaysAgo": "90 દિવસ પહેલાં",
  "54DaysAgo": "54 દિવસ પહેલાં",
  "48DaysAgo": "48 દિવસ પહેલાં",
  "38DaysAgo": "38 દિવસ પહેલાં",
  "automatedIncidentTitle": "આ ક્ષણે ઍક્સેસ કરી શકાતું નથી (સ્વચાલિત)",
  "automatedIncidentMessage": "આ ક્ષણે ઍક્સેસ કરી શકાતું નથી. આ ઘટના સ્વચાલિત નિરીક્ષણ સેવા દ્વારા બનાવવામાં આવી હતી.",
  "automatedResolveMessage": "હવે કાર્યરત છે! આ અપડેટ સ્વચાલિત નિરીક્ષણ સેવા દ્વારા બનાવવામાં આવ્યું હતું.",
  "statusUpdates": "સ્થિતિ અપડેટ્સ",
  "hasANewIncident": "ની એક નવી ઘટના છે",
  "openStatusPage": "સ્થિતિ પૃષ્ઠ ખોલો",
  "youreReceivingThisEmailBecauseYouSubscribed": "તમને આ ઇમેઇલ એટલા માટે મળી રહ્યો છે કારણ કે તમે આ માટે સબ્સ્ક્રાઇબ કર્યું હતું ",
  "pleaseConfirmYourSubscription": "તમારા સબ્સ્ક્રિપ્શનની પુષ્ટિ કરવા માટે કૃપા કરીને અહીં ક્લિક કરો",
  "incidentUpdates": "ઘટના અપડેટ્સ",
  "youCan": "તમે",
  "unsubscribe": "અનસબ્સ્ક્રાઇબ કરો",
  "unsubscribeNotice": "અનસબ્સ્ક્રાઇબ કરો: ",
  "here": "અહીં",
  "checkItOut": "તેને જુઓ",
  "useThisLink": "આ લિંકનો ઉપયોગ કરો",
  "hasUpdatedTheirIncident": "એ તેમની ઘટના અપડેટ કરી છે",
  "scheduledANewMaintenance": "એ એક નવી જાળવણી નિર્ધારિત કરી છે",
  "updatedTheirMaintenance": "એ તેમની જાળવણી અપડેટ કરી છે",
  "resecheduledMaintenance": "એ તેમની જાળવણી ફરીથી નિર્ધારિત કરી છે",
  "maintenanceNotStarted": "અમે તે સમય દરમિયાન એક નિર્ધારિત જાળવણીનું આયોજન કરી રહ્યા છીએ",
  "maintenanceInProgress": "જાળવણી હવે ચાલુ છે",
  "maintenanceComplete": "જાળવણી સફળતાપૂર્વક પૂર્ણ થઈ છે",
  "viewMaintenance": "જાળવણી જુઓ",
  "viewIncident": "ઘટના જુઓ",
  "impact": "અસર",
  "maintenanceWillBeginSoon": "જાળવણી {{minutes}} મિનિટમાં શરૂ થશે",
  "maintenanceWillBeginAfter": "જાળવણી {{time}} માં શરૂ થશે",
  "postmortem": "પોસ્ટમોર્ટમ",
  "recentNotices": "તાજેતરની સૂચનાઓ",
  "showNoticeHistory": "સૂચના ઇતિહાસ બતાવો",
  "noticeHistory": "સૂચના ઇતિહાસ",
  "noNotices": "કોઈ સૂચના નોંધાઈ નથી",
  "noNoticesDays": "છેલ્લા {{days}} દિવસમાં કોઈ સૂચના નોંધાઈ નથી",
  "noNoticesMonth": "આ મહિને કોઈ સૂચના નોંધાઈ નથી",
  "starts": "શરૂ થાય છે",
  "duration": "અવધિ",
  "viewLatestUpdates": "નવીનતમ અપડેટ્સ જુઓ",
  "lastUpdated": "છેલ્લે {{time}} પહેલાં અપડેટ થયું",
  "year": "વર્ષ",
  "years": "વર્ષો",
  "month": "મહિનો",
  "months": "મહિના",
  "day": "દિવસ",
  "days": "દિવસો",
  "hour": "કલાક",
  "hours": "કલાકો",
  "minute": "મિનિટ",
  "minutes": "મિનિટ",
  "second": "સેકન્ડ",
  "seconds": "સેકન્ડ",
  "getNoticeUpdates": "આ સૂચના માટે અપડેટ્સ મેળવો",
  "subscribeToAll": "તેના બદલે બધી સ્થિતિ પૃષ્ઠ અપડેટ્સ સબ્સ્ક્રાઇબ કરો",
  "phoneNumber": "ફોન નંબર",
  "findAService": "એક સેવા શોધો",
  "noIssuesReportedYet": "હજુ કોઈ સમસ્યા નોંધાઈ નથી",
  "peopleReportedThis": "છેલ્લા કલાકમાં {{number}} લોકોએ આની જાણ કરી",
  "peopleVisitedThisPage": "{{number}} લોકો અત્યારે આ પૃષ્ઠ તપાસી રહ્યા છે",
  "hotRightNow": "અત્યારે ચર્ચામાં",
  "services": "સેવાઓ",
  "favorites": "મનપસંદ",
  "loadMore": "વધુ લોડ કરો",
  "isXDown": "શું {{service}} ડાઉન છે?",
  "iHaveAnIssueToo": "મને પણ એક સમસ્યા છે",
  "serviceIsDown": "{{service}} ડાઉન છે",
  "serviceIsUp": "{{service}} ચાલુ છે",
  "done": "થઈ ગયું",
  "selectAComponent": "એક ઘટક પસંદ કરો",
  "noServicesFound": "કોઈ સેવા મળી નથી",
  "reports": "{{number}} અહેવાલો",
  "changeTheme": "થીમ બદલો",
  "goToHome": "હોમ પર જાઓ",
  "partiallyDegradedService": "આંશિક રીતે ઘટેલી સેવા",
  "partialSystemOutage": "આંશિક સિસ્ટમ આઉટેજ",
  "majorSystemOutage": "મોટી સિસ્ટમ આઉટેજ",
  "experiencingMajorOutage": "મોટી આઉટેજનો અનુભવ થઈ રહ્યો છે",
  "experiencingPartialOutage": "આંશિક આઉટેજનો અનુભવ થઈ રહ્યો છે",
  "experiencingDegradedPerformance": "ઘટેલા પ્રદર્શનનો અનુભવ થઈ રહ્યો છે",
  "experiencingMinorOutage": "નાની આઉટેજનો અનુભવ થઈ રહ્યો છે",
  "experiencingPartiallyDegradedPerformance": "આંશિક રીતે ઘટેલા પ્રદર્શનનો અનુભવ થઈ રહ્યો છે",
  "systemUnderMaintenance": "સિસ્ટમ જાળવણી હેઠળ છે",
  "componentExperiencingMajorOutage": "{{component}} માં મોટી આઉટેજનો અનુભવ થઈ રહ્યો છે",
  "componentExperiencingPartialOutage": "{{component}} માં આંશિક આઉટેજનો અનુભવ થઈ રહ્યો છે",
  "componentExperiencingDegradedPerformance": "{{component}} માં ઘટેલા પ્રદર્શનનો અનુભવ થઈ રહ્યો છે",
  "componentUnderMaintenance": "{{component}} જાળવણી હેઠળ છે",
  "week": "અઠવાડિયું",
  "weeks": "અઠવાડિયા",
  "systemMetricsNoData": "આ સમયગાળા માટે હજુ કોઈ ડેટા ઉમેરાયો નથી",
  "googleChat": "Google Chat",
  "getUpdatesGoogleChatShort": "તમારી સ્પેસમાં અપડેટ્સ મેળવો",
  "getUpdatesGoogleChatLong": "તમારી સ્પેસમાં અપડેટ્સ મેળવો",
  "learnGoogleChatWebhook": "તમારી Google Chat સ્પેસમાં webhook કેવી રીતે ઉમેરવું તે શીખો",
  "googleChatSend": "જ્યારે અમે અમારી સ્થિતિ અપડેટ કરીએ છીએ, ત્યારે અમે તમારી Google Chat સ્પેસમાં અપડેટ્સ મોકલીશું.",
  "ourPublicAPI": "અમારું સાર્વજનિક API",
  "summary": "તમારા સ્થિતિ પૃષ્ઠની એકંદર સ્થિતિ મેળવો. તેમાં ઘટકો અને ઐતિહાસિક સૂચનાઓ શામેલ નથી.",
  "components": "તમારા સ્થિતિ પૃષ્ઠના ઘટકો અને તેમને અસર કરતી સક્રિય સમસ્યાઓ મેળવો.",
  "API": "API",
  "noRelatedNotices": "કોઈ સંબંધિત સૂચનાઓ નથી",
  "customizeRequest": "વિનંતી કસ્ટમાઇઝ કરો",
  "lasted": "ચાલ્યું",
  "updates": "અપડેટ્સ",
  "readMore": "વધુ વાંચો",
  "issue": "સમસ્યા",
  "issues": "સમસ્યાઓ",
  "skipUptimeGraph": "અપટાઇમ ગ્રાફ છોડો",
  "readUptimeGraph": "અપટાઇમ ગ્રાફ વાંચો",
  "reachedTheEndOfUptimeGraph": "તમે {{component}} માટે અપટાઇમ ગ્રાફના અંતે પહોંચી ગયા છો",
  "Incident": "ઘટના",
  "oneMaintenanceIsScheduled": "એક જાળવણી નિર્ધારિત છે",
  "multipleMaintenancePeriodsAreScheduled": "{{multiple}} જાળવણી સમયગાળા નિર્ધારિત છે",
  "investigatingIncidentPlaceholderDescription": "અમે હાલમાં આ ઘટનાની તપાસ કરી રહ્યા છીએ.",
  "identifiedIncidentPlaceholderDescription": "અમે આ ઘટના માટે ઉકેલ પર કામ કરવાનું ચાલુ રાખી રહ્યા છીએ.",
  "monitoringIncidentPlaceholderDescription": "અમે એક ઉકેલ લાગુ કર્યો છે અને હાલમાં પરિણામનું નિરીક્ષણ કરી રહ્યા છીએ.",
  "resolvedIncidentPlaceholderDescription": "આ ઘટના ઉકેલાઈ ગઈ છે.",
  "unsubscribed": "તમે અનસબ્સ્ક્રાઇબ થયા છો",
  "unsubscribedDescription": "તમને હવે સ્થિતિ અપડેટ્સ મળશે નહીં",
  "unsubscribeError": "અનસબ્સ્ક્રાઇબ નિષ્ફળ થયું",
  "unsubscribeDetailedError": "આ અનસબ્સ્ક્રાઇબ લિંક હવે સક્રિય નથી. કદાચ તમે પહેલેથી જ તમારી અનસબ્સ્ક્રાઇબ વિનંતી પૂર્ણ કરી દીધી હશે.",
  "genericNotice": "સામાન્ય સૂચના",
  "genericNotices": "સામાન્ય સૂચનાઓ",
  "noticeDetails": "સૂચના વિગતો",
  "Posted": "પોસ્ટ કર્યું",
  "manageSubscription": "સબ્સ્ક્રિપ્શન સંચાલિત કરો",
  "manageYourSubscription": "તમારું સબ્સ્ક્રિપ્શન સંચાલિત કરો",
  "manageComponentsYouAreSubscribedTo": "તમે જે ઘટકો સબ્સ્ક્રાઇબ કર્યા છે તેને સંચાલિત કરો",
  "manageYourNotificationSettings": "તમારી સૂચના સેટિંગ્સ સંચાલિત કરો →",
  "repeatsDaily": "દરરોજ પુનરાવર્તિત થાય છે",
  "repeatsWeekdays": "અઠવાડિયાના દિવસોમાં પુનરાવર્તિત થાય છે",
  "repeatsWeekly": "દર અઠવાડિયે પુનરાવર્તિત થાય છે",
  "repeatsMonthly": "દર મહિને પુનરાવર્તિત થાય છે",
  "repeatsYearly": "દર વર્ષે પુનરાવર્તિત થાય છે",
  "justNow": "હમણાં જ",
  "minutesAgo": "{{count}}મિ પહેલાં",
  "hoursAgo": "{{count}}ક પહેલાં",
  "translate": "અનુવાદ કરો",
  "showOriginal": "મૂળ બતાવો",
  "translating": "અનુવાદ થઈ રહ્યો છે...",
  "downloadingTranslationModel": "અનુવાદ મોડેલ ડાઉનલોડ થઈ રહ્યું છે...",
  "percentComplete": "{{pct}}% પૂર્ણ",
  "translationFailed": "અનુવાદ નિષ્ફળ થયો",
  "yourName": "તમારું નામ",
  "addAComment": "એક ટિપ્પણી ઉમેરો...",
  "sendComment": "ટિપ્પણી મોકલો",
  "sending": "મોકલાઈ રહ્યું છે...",
  "loading": "લોડ થઈ રહ્યું છે...",
  "pleaseFillAllFields": "કૃપા કરીને બધા ક્ષેત્રો ભરો",
  "commentPosted": "ટિપ્પણી પોસ્ટ થઈ",
  "failedToPostComment": "ટિપ્પણી પોસ્ટ કરવામાં નિષ્ફળ",
  "addedToFavorites": "મનપસંદમાં ઉમેર્યું",
  "removedFromFavorites": "મનપસંદમાંથી દૂર કર્યું",
  "addToFavorites": "મનપસંદમાં ઉમેરો",
  "removeFromFavorites": "મનપસંદમાંથી દૂર કરો",
  "failedToSubmitReport": "અહેવાલ સબમિટ કરવામાં નિષ્ફળ",
  "thankYouForReport": "અહેવાલ માટે આભાર!",
  "wantToLeaveComment": "શું તમે આ સમસ્યા વિશે ટિપ્પણી મૂકવા માંગો છો?",
  "describeIssue": "તમે જે સમસ્યાનો અનુભવ કરી રહ્યા છો તેનું વર્ણન કરો...",
  "posting": "પોસ્ટ થઈ રહ્યું છે...",
  "postComment": "ટિપ્પણી પોસ્ટ કરો",
  "skip": "છોડો",
  "suggestAddingIt": "તેને ઉમેરવાનું સૂચન કરો!",
  "suggestServiceTitle": "અમારા ઉમેરવા માટે એક સેવા સૂચવો!",
  "serviceName": "સેવાનું નામ",
  "websiteUrl": "વેબસાઇટ URL",
  "submit": "સબમિટ કરો",
  "cancel": "રદ કરો",
  "thankYou": "આભાર!",
  "suggestionReceived": "અમે તમારા સૂચનની સમીક્ષા કરીશું અને જો તે યોગ્ય હશે તો તેને ઉમેરીશું.",
  "close": "બંધ કરો",
  "pleaseEnterServiceName": "કૃપા કરીને સેવાનું નામ દાખલ કરો",
  "somethingWentWrong": "કંઈક ખોટું થયું",
  "switchToLightMode": "લાઇટ મોડ પર સ્વિચ કરો",
  "switchToDarkMode": "ડાર્ક મોડ પર સ્વિચ કરો",
  "allServices": "બધી સેવાઓ",
  "thatsAll": "બસ આટલું જ",
  "serviceNotFoundDescription": "તમે જે સેવા શોધી રહ્યા છો તે અસ્તિત્વમાં નથી અથવા હજુ ઉમેરાઈ નથી.",
  "slackSend": "જ્યારે અમે અમારી સ્થિતિ અપડેટ કરીએ છીએ, ત્યારે અમે તમારી Slack ચેનલમાં અપડેટ્સ મોકલીશું.",
  "discordSend": "જ્યારે અમે અમારી સ્થિતિ અપડેટ કરીએ છીએ, ત્યારે અમે તમારી Discord ચેનલમાં અપડેટ્સ મોકલીશું.",
  "homepageTitle": "{{siteName}} – શું તે ડાઉન છે? રીઅલ-ટાઇમ સેવા સ્થિતિ",
  "homepageDescription": "સેંકડો લોકપ્રિય સેવાઓ માટે રીઅલ-ટાઇમ સ્થિતિ નિરીક્ષણ. તપાસો કે કોઈ સેવા ડાઉન છે કે નહીં, આઉટેજ અહેવાલો જુઓ, અને 12-કલાકનો સ્થિતિ ઇતિહાસ જુઓ.",
  "homepageTwitterDescription": "હજારો લોકપ્રિય સેવાઓ માટે વપરાશકર્તા અહેવાલો પર આધારિત રીઅલ-ટાઇમ સ્થિતિ. આઉટેજ તપાસો અને 12-કલાકનો ઇતિહાસ જુઓ.",
  "homepageOgImageAlt": "{{siteName}} – વપરાશકર્તા અહેવાલો પર આધારિત રીઅલ-ટાઇમ સ્થિતિ",
  "homepageJsonLdDescription": "રીઅલ-ટાઇમ સેવા સ્થિતિ નિરીક્ષણ. તપાસો કે લોકપ્રિય સેવાઓ ડાઉન છે કે નહીં અને આઉટેજ અહેવાલો જુઓ.",
  "popularServices": "લોકપ્રિય સેવાઓ",
  "serviceNotFoundTitle": "સેવા મળી નથી – {{siteName}}",
  "isServiceDownQuestion": "શું {{service}} ડાઉન છે?",
  "serviceStatusDescriptionDown": "{{service}} હાલમાં ડાઉન છે. રીઅલ-ટાઇમ સ્થિતિ તપાસો, {{count}} તાજેતરના આઉટેજ અહેવાલો જુઓ, અને 12-કલાકનો ઇતિહાસ ચાર્ટ જુઓ.",
  "serviceStatusDescriptionUp": "{{service}} હાલમાં ચાલુ છે. રીઅલ-ટાઇમ સ્થિતિ તપાસો, {{count}} તાજેતરના આઉટેજ અહેવાલો જુઓ, અને 12-કલાકનો ઇતિહાસ ચાર્ટ જુઓ.",
  "serviceAnnouncementNameDown": "{{service}} માં સમસ્યાઓનો અનુભવ થઈ રહ્યો છે",
  "serviceAnnouncementNameUp": "{{service}} કાર્યરત છે",
  "serviceAnnouncementHeadlineDown": "{{service}} આઉટેજ નોંધાઈ",
  "serviceAnnouncementHeadlineUp": "{{service}} ચાલુ અને કાર્યરત છે",
  "serviceAnnouncementTextDown": "{{service}} માં હાલમાં સમસ્યાઓનો અનુભવ થઈ રહ્યો છે. છેલ્લા કલાકમાં {{count}} વપરાશકર્તા અહેવાલો સબમિટ થયા છે. {{url}} પર લાઇવ સ્થિતિ અને 12-કલાકનો અહેવાલ ચાર્ટ જુઓ.",
  "serviceAnnouncementTextUp": "{{service}} હાલમાં કાર્યરત છે. છેલ્લા કલાકમાં {{count}} વપરાશકર્તા અહેવાલો સબમિટ થયા છે. {{url}} પર લાઇવ સ્થિતિ અને 12-કલાકનો અહેવાલ ચાર્ટ જુઓ.",
  "serviceFaqDownQuestion": "શું {{service}} અત્યારે ડાઉન છે?",
  "serviceFaqStatusAnswerDown": "{{service}} માં હાલમાં સમસ્યાઓનો અનુભવ થઈ રહ્યો છે. છેલ્લા કલાકમાં {{count}} વપરાશકર્તા અહેવાલો થયા છે. {{url}} પર લાઇવ સ્થિતિ અને 12-કલાકનો અહેવાલ ચાર્ટ તપાસો.",
  "serviceFaqStatusAnswerUp": "{{service}} હાલમાં કાર્યરત છે. છેલ્લા કલાકમાં {{count}} વપરાશકર્તા અહેવાલો થયા છે. {{url}} પર લાઇવ સ્થિતિ અને 12-કલાકનો અહેવાલ ચાર્ટ તપાસો.",
  "serviceFaqHowToCheckQuestion": "{{service}} ડાઉન છે કે નહીં તે કેવી રીતે તપાસવું?",
  "serviceFaqHowToCheckAnswer": "{{service}} ની રીઅલ-ટાઇમ સ્થિતિ જોવા માટે {{url}} ની મુલાકાત લો. આ પૃષ્ઠ વપરાશકર્તાઓ દ્વારા સબમિટ કરેલા લાઇવ આઉટેજ અહેવાલો અને 12-કલાકનો ઇતિહાસ ચાર્ટ બતાવે છે જેથી તમે જાણી શકો કે {{service}} ડાઉન છે કે સમસ્યાઓ આવી રહી છે.",
  "breadcrumbHome": "હોમ",
  "serviceWebPageName": "શું {{service}} ડાઉન છે? – {{service}} સ્થિતિ",
  "serviceWebPageDescription": "{{service}} માટે રીઅલ-ટાઇમ સ્થિતિ અને આઉટેજ નિરીક્ષણ. જુઓ કે {{service}} ડાઉન છે કે નહીં અને અહેવાલ ઇતિહાસ જુઓ.",
  "monitorYourWebsiteWithInstatus": "Instatus સાથે તમારી પોતાની વેબસાઇટનું નિરીક્ષણ કરો!",
  "fromInstatus": "Instatus.com તરફથી",
  "search": "શોધો…",
  "noOptions": "કોઈ વિકલ્પ નથી",
  "yourTimezone": "તમારો ટાઇમ ઝોન",
  "chooseTimezone": "ટાઇમ ઝોન પસંદ કરો"
}
